ts2python/__init__.py
ts2python/json_validation.py
ts2python/singledispatch_shim.py
ts2python/typeddict_shim.py
ts2python/typeddict_shim.py_313
ts2python/typeddict_shim.py_314
ts2python/typing_extensions.py
ts2python.ebnf
ts2pythonConfig.ini
ts2pythonExplorer.py
ts2pythonParser.py
ts2python-0.8.1.dist-info/LICENSE
ts2python-0.8.1.dist-info/METADATA
ts2python-0.8.1.dist-info/WHEEL
ts2python-0.8.1.dist-info/entry_points.txt
ts2python-0.8.1.dist-info/RECORD
