Metadata-Version: 2.3
Name: ts2python
Version: 0.8.1
Summary: Python-Interoperability for Typescript-Interfaces
License: Apache-2.0
Keywords: Typescript to Python converter,Typescript Interface,Python TypedDict
Author: Eckhart Arnold
Author-email: eckhart.arnold@posteo.de
Requires-Python: >=3.8,<4.0
Classifier: Development Status :: 5 - Production/Stable
Classifier: Environment :: Console
Classifier: Intended Audience :: Developers
Classifier: License :: OSI Approved :: Apache Software License
Classifier: Operating System :: OS Independent
Classifier: Programming Language :: Python :: 3
Classifier: Programming Language :: Python :: 3.8
Classifier: Programming Language :: Python :: 3.9
Classifier: Programming Language :: Python :: 3.10
Classifier: Programming Language :: Python :: 3.11
Classifier: Programming Language :: Python :: 3.12
Classifier: Programming Language :: Python :: 3.13
Classifier: Programming Language :: Python :: 3.14
Classifier: Programming Language :: Python :: Implementation :: CPython
Classifier: Programming Language :: Python :: Implementation :: PyPy
Classifier: Topic :: Software Development :: Code Generators
Classifier: Topic :: Software Development :: Compilers
Classifier: Topic :: Text Processing :: Markup
Requires-Dist: DHParser (>=1.9.1,<2.0.0)
Project-URL: Homepage, https://github.com/jecki/ts2python
Project-URL: Repository, https://github.com/jecki/ts2python
